fabric_lite/__init__.py
fabric_lite/main.py
fabric_lite-0.1.0.dist-info/LICENSE.txt
fabric_lite-0.1.0.dist-info/METADATA
fabric_lite-0.1.0.dist-info/WHEEL
fabric_lite-0.1.0.dist-info/RECORD
