Metadata-Version: 2.3
Name: fabric-lite
Version: 0.1.0
Summary: Fabric Lite это простой cli интерфейс для взаимодействия с LLM, вдохновленный Fabric.
License: MIT
Author: Forwall100
Author-email: hezeri546@gmail.com
Requires-Python: >=3.12
Classifier: License :: OSI Approved :: MIT License
Classifier: Programming Language :: Python :: 3
Classifier: Programming Language :: Python :: 3.12
Classifier: Programming Language :: Python :: 3.13
Requires-Dist: click (>=8.2.1,<9.0.0)
Requires-Dist: requests (>=2.32.4,<3.0.0)
